.gitignore
AUTHORS
CHANGELOG.txt
LICENSE
MANIFEST.in
Makefile
README.rst
setup.cfg
setup.py
.vscode/setup.json
docs/index.html
docs/ispapi.connection.html
docs/ispapi.html
docs/ispapi.response.html
docs/ispapi.util.html
ispapi/__init__.py
ispapi/connection.py
ispapi/response.py
ispapi/util.py
ispapi.egg-info/PKG-INFO
ispapi.egg-info/SOURCES.txt
ispapi.egg-info/dependency_links.txt
ispapi.egg-info/not-zip-safe
ispapi.egg-info/requires.txt
ispapi.egg-info/top_level.txt
source/conf.py
source/index.rst